[
  {"model": "documents.documenttype", "pk": "invoice", "fields": {"label": "Rechnung (eingehend/ausgehend)"}},
  {"model": "documents.documenttype", "pk": "shipping_document", "fields": {"label": "Versandbeleg / Lieferschein / Paketschein"}},
  {"model": "documents.documenttype", "pk": "contract", "fields": {"label": "Vertrag / Vereinbarung (inkl. Ehe-/Erbvertrag, Testament)"}},
  {"model": "documents.documenttype", "pk": "legal_document", "fields": {"label": "Rechtsdokument / Behörde / Gericht"}},
  {"model": "documents.documenttype", "pk": "technical_documentation", "fields": {"label": "Technische Dokumentation / Gefahrenbeurteilung"}},
  {"model": "documents.documenttype", "pk": "payroll", "fields": {"label": "Lohn- / Gehaltsabrechnung"}},
  {"model": "documents.documenttype", "pk": "inventory_report", "fields": {"label": "Inventur / Lagerbestand"}},
  {"model": "documents.documenttype", "pk": "financial_statement", "fields": {"label": "Jahresabschluss / BWA / GuV"}},
  {"model": "documents.documenttype", "pk": "tax_return", "fields": {"label": "Steuermeldung / UStVA / Dauerfrist"}},
  {"model": "documents.documenttype", "pk": "shareholder_meeting", "fields": {"label": "Gesellschafterversammlung / GbR-Beschluss"}},
  {"model": "documents.documenttype", "pk": "price_list", "fields": {"label": "Preisliste / Katalog / Angebotstarif"}},
  {"model": "documents.documenttype", "pk": "medical_record", "fields": {"label": "Medizinische Unterlagen / Rentenbescheide"}},
  {"model": "documents.documenttype", "pk": "prescription", "fields": {"label": "Rezepte (Arzt)"}},
  {"model": "documents.documenttype", "pk": "property_document", "fields": {"label": "Haus & Grundstück (Grundbuch, Bescheinigungen)"}},
  {"model": "documents.documenttype", "pk": "certificate", "fields": {"label": "Bescheinigungen & Urkunden (Zeugnisse, Geburtsurkunde)"}},
  {"model": "documents.documenttype", "pk": "correspondence", "fields": {"label": "Korrespondenz & Briefe"}},
  {"model": "documents.documenttype", "pk": "bank_statement", "fields": {"label": "Kontoauszug & Finanzbelege"}},
  {"model": "documents.documenttype", "pk": "photo_archive", "fields": {"label": "Fotos & Erinnerungen"}},
  {"model": "documents.documenttype", "pk": "customer_feedback", "fields": {"label": "Kunden-Feedback / Erfahrungsbericht"}},
  {"model": "documents.documenttype", "pk": "research_report", "fields": {"label": "Forschungs-/Prüfbericht / Statistik"}},
  {"model": "documents.documenttype", "pk": "media_contract", "fields": {"label": "Medienvertrag / Model-Release / KSK"}},
  {"model": "documents.documenttype", "pk": "script_data", "fields": {"label": "Scripte / Rohdaten / Statistik-Dateien"}},
  {"model": "documents.documenttype", "pk": "academic_record", "fields": {"label": "Studien-/Ausbildungsunterlagen & Leistungsnachweise"}},
  {"model": "documents.documenttype", "pk": "customer_project", "fields": {"label": "Kundenprojekt / Beratung / individuelles Projekt"}},
  {"model": "documents.documenttype", "pk": "software_license", "fields": {"label": "Software-Lizenz / Wartungsvertrag"}}
]
